pytan3/__init__.py
pytan3/exceptions.py
pytan3/version.py
pytan3/adapters/__init__.py
pytan3/adapters/exceptions.py
pytan3/api_clients/__init__.py
pytan3/api_clients/exceptions.py
pytan3/api_models/__init__.py
pytan3/api_models/exceptions.py
pytan3/api_objects/__init__.py
pytan3/api_objects/exceptions.py
pytan3/api_objects/rest_7_3_314_3424.py
pytan3/api_objects/rest_7_3_314_3641.py
pytan3/api_objects/soap_7_2_314_3181.py
pytan3/api_objects/soap_7_3_314_3424.py
pytan3/api_objects/soap_7_3_314_3641.py
pytan3/api_objects/build_objects/__init__.py
pytan3/api_objects/build_objects/build_objects_from_wsdl.py
pytan3/api_objects/build_objects/download_console_wsdl.py
pytan3/api_objects/build_objects/7_2_314_3181/__init__.py
pytan3/api_objects/build_objects/7_2_314_3181/soap.py
pytan3/api_objects/build_objects/7_3_314_3424/__init__.py
pytan3/api_objects/build_objects/7_3_314_3424/rest.py
pytan3/api_objects/build_objects/7_3_314_3424/soap.py
pytan3/api_objects/build_objects/7_3_314_3641/__init__.py
pytan3/api_objects/build_objects/7_3_314_3641/rest.py
pytan3/api_objects/build_objects/7_3_314_3641/soap.py
pytan3/auth_methods/__init__.py
pytan3/auth_methods/exceptions.py
pytan3/auth_store/__init__.py
pytan3/auth_store/exceptions.py
pytan3/http_client/__init__.py
pytan3/http_client/exceptions.py
pytan3/results/__init__.py
pytan3/results/exceptions.py
pytan3/tests/__init__.py
pytan3/tests/conftest.py
pytan3/tests/certs/__init__.py
pytan3/tests/certs/build_certs.py
pytan3/tests/test_adapters/__init__.py
pytan3/tests/test_adapters/test_adapter_rest.py
pytan3/tests/test_adapters/test_adapter_soap.py
pytan3/tests/test_adapters/test_adapters_all.py
pytan3/tests/test_adapters/test_adapters_all_rest.py
pytan3/tests/test_adapters/test_adapters_all_soap.py
pytan3/tests/test_api_clients/__init__.py
pytan3/tests/test_api_clients/test_api_clients.py
pytan3/tests/test_api_objects/__init__.py
pytan3/tests/test_api_objects/build_data_sets.py
pytan3/tests/test_api_objects/data_sets.py
pytan3-3.0.0.dist-info/LICENSE
pytan3-3.0.0.dist-info/METADATA
pytan3-3.0.0.dist-info/WHEEL
pytan3-3.0.0.dist-info/top_level.txt
pytan3-3.0.0.dist-info/RECORD
