Metadata-Version: 2.1
Name: pytan3
Version: 3.0.0
Summary: Tanium API workflow encapsulation.
Home-page: https://github.com/tanium/pytan3
Author: Jim Olsen
Author-email: jim.olsen@tanium.com
License: MIT
Platform: UNKNOWN
Classifier: Development Status :: 5 - Production/Stable
Classifier: Intended Audience :: Developers
Classifier: Natural Language :: English
Classifier: License :: OSI Approved :: MIT License
Classifier: Programming Language :: Python
Classifier: Programming Language :: Python :: 2
Classifier: Programming Language :: Python :: 2.7
Classifier: Programming Language :: Python :: 3
Classifier: Programming Language :: Python :: 3.7
Classifier: Programming Language :: Python :: Implementation :: CPython
Classifier: Programming Language :: Python :: Implementation :: PyPy
Requires-Python: >=2.7, !=3.0.*, !=3.1.*, !=3.2.*, !=3.3.*
Requires-Dist: cert-human
Requires-Dist: colorama
Requires-Dist: humanfriendly
Requires-Dist: privy
Requires-Dist: requests[security,socks]
Requires-Dist: six (>=1.12.0)
Requires-Dist: xmltodict
Requires-Dist: python-dotenv
Requires-Dist: pathlib2 ; python_version < "3.0"
